macad_gym/__init__.py
macad_gym/multi_actor_env.py
macad_gym/carla/Transform.py
macad_gym/carla/__init__.py
macad_gym/carla/multi_env.py
macad_gym/carla/reward.py
macad_gym/carla/scenarios.py
macad_gym/carla/spawn_control.py
macad_gym/carla/PythonAPI/__init__.py
macad_gym/carla/PythonAPI/converter.py
macad_gym/carla/PythonAPI/dynamic_weather.py
macad_gym/carla/PythonAPI/manual_control.py
macad_gym/carla/PythonAPI/scenarios.py
macad_gym/carla/PythonAPI/settings.py
macad_gym/carla/PythonAPI/setup.py
macad_gym/carla/PythonAPI/tutorial.py
macad_gym/carla/PythonAPI/vehicle_gallery.py
macad_gym/carla/PythonAPI/agents/__init__.py
macad_gym/carla/PythonAPI/agents/navigation/__init__.py
macad_gym/carla/PythonAPI/agents/navigation/agent.py
macad_gym/carla/PythonAPI/agents/navigation/basic_agent.py
macad_gym/carla/PythonAPI/agents/navigation/controller.py
macad_gym/carla/PythonAPI/agents/navigation/global_route_planner.py
macad_gym/carla/PythonAPI/agents/navigation/global_route_planner_dao.py
macad_gym/carla/PythonAPI/agents/navigation/local_planner.py
macad_gym/carla/PythonAPI/agents/navigation/roaming_agent.py
macad_gym/carla/PythonAPI/agents/navigation/test_global_route_planner.py
macad_gym/carla/PythonAPI/agents/tools/__init__.py
macad_gym/carla/PythonAPI/agents/tools/misc.py
macad_gym/carla/PythonAPI/test/__init__.py
macad_gym/carla/PythonAPI/test/test_client.py
macad_gym/carla/PythonAPI/test/test_transform.py
macad_gym/carla/PythonAPI/test/test_vehicle.py
macad_gym/core/__init__.py
macad_gym/core/vehicle_manager.py
macad_gym/core/controllers/__init__.py
macad_gym/core/controllers/keyboard_control.py
macad_gym/core/controllers/traffic_lights.py
macad_gym/core/maps/__init__.py
macad_gym/core/maps/nav_utils.py
macad_gym/core/maps/nodeid_coord_map.py
macad_gym/core/sensors/__init__.py
macad_gym/core/sensors/camera_manager.py
macad_gym/core/sensors/derived_sensors.py
macad_gym/core/sensors/hud.py
macad_gym/core/sensors/utils.py
macad_gym/envs/__init__.py
macad_gym-0.1.4.dist-info/LICENSE
macad_gym-0.1.4.dist-info/METADATA
macad_gym-0.1.4.dist-info/WHEEL
macad_gym-0.1.4.dist-info/top_level.txt
macad_gym-0.1.4.dist-info/RECORD
