Metadata-Version: 2.1
Name: macad-gym
Version: 0.1.4
Summary: Learning environments for Multi-Agent Connected Autonomous Driving (MACAD) with OpenAI Gym compatible interfaces
Home-page: https://github.com/praveen-palanisamy/macad-gym
Author: Praveen Palanisamy
Author-email: praveen.palanisamy@outlook.com
License: UNKNOWN
Project-URL: Source, https://github.com/praveen-palanisamy/macad-gym
Project-URL: Report bug, https://github.com/praveen-palanisamy/macad-gym/issues
Project-URL: Author website, https://praveenp.com
Keywords: multi-agent learning environments connected autonomous driving OpenAI Gym CARLA
Platform: UNKNOWN
Classifier: Development Status :: 3 - Alpha
Classifier: Programming Language :: Python :: 3
Classifier: Programming Language :: Python :: 3.5
Classifier: Programming Language :: Python :: 3.6
Classifier: Programming Language :: Python :: 3.7
Classifier: Programming Language :: Python :: 3.8
Classifier: Programming Language :: Python :: 3.9
Classifier: Intended Audience :: Science/Research
Classifier: Intended Audience :: Developers
Classifier: Intended Audience :: Education
Classifier: License :: OSI Approved :: MIT License
Classifier: Topic :: Scientific/Engineering
Classifier: Topic :: Scientific/Engineering :: Artificial Intelligence
Requires-Python: >=3.0
Requires-Dist: gym
Requires-Dist: carla (>=0.9.3)
Requires-Dist: GPUtil
Requires-Dist: pygame
Requires-Dist: opencv-python
Requires-Dist: networkx
Provides-Extra: test
Requires-Dist: tox ; extra == 'test'
Requires-Dist: pytest ; extra == 'test'
Requires-Dist: pytest-xdist ; extra == 'test'
